odoo/addons/account_period_lock_date_multi_company/README.rst
odoo/addons/account_period_lock_date_multi_company/__init__.py
odoo/addons/account_period_lock_date_multi_company/__manifest__.py
odoo/addons/account_period_lock_date_multi_company/i18n/account_period_lock_date_multi_company.pot
odoo/addons/account_period_lock_date_multi_company/i18n/fr.po
odoo/addons/account_period_lock_date_multi_company/i18n/it.po
odoo/addons/account_period_lock_date_multi_company/readme/CONFIGURE.rst
odoo/addons/account_period_lock_date_multi_company/readme/CONTRIBUTORS.rst
odoo/addons/account_period_lock_date_multi_company/readme/DESCRIPTION.rst
odoo/addons/account_period_lock_date_multi_company/static/description/icon.png
odoo/addons/account_period_lock_date_multi_company/static/description/index.html
odoo/addons/account_period_lock_date_multi_company/static/description/res_company_tree.png
odoo/addons/account_period_lock_date_multi_company/views/view_res_company.xml
odoo_addon_account_period_lock_date_multi_company-16.0.1.0.0.4.dist-info/METADATA
odoo_addon_account_period_lock_date_multi_company-16.0.1.0.0.4.dist-info/WHEEL
odoo_addon_account_period_lock_date_multi_company-16.0.1.0.0.4.dist-info/top_level.txt
odoo_addon_account_period_lock_date_multi_company-16.0.1.0.0.4.dist-info/RECORD
